{
  "project_info": {
    "project_number": "658899465592",
    "firebase_url": "https://finddog-3ca91-default-rtdb.firebaseio.com",
    "project_id": "finddog-3ca91",
    "storage_bucket": "finddog-3ca91.appspot.com"
  },
  "client": [
    {
      "client_info": {
        "mobilesdk_app_id": "1:658899465592:android:3480fa4edcc4cd1f8b848d",
        "android_client_info": {
          "package_name": "ie.tud.finddog"
        }
      },
      "oauth_client": [
        {
          "client_id": "658899465592-tk0mgpno1g4cm2psu34c2ip97b1pvga0.apps.googleusercontent.com",
          "client_type": 1,
          "android_info": {
            "package_name": "ie.tud.finddog",
            "certificate_hash": "59b79ec719a46afeab52e26b69faa72387952ffd"
          }
        },
        {
          "client_id": "658899465592-4itlloc65cfnbum9m84co0bb621ap7l0.apps.googleusercontent.com",
          "client_type": 3
        }
      ],
      "api_key": [
        {
          "current_key": "AIzaSyB7g0ulcKnF_pF9SH-59E91GO5DMlffxbI"
        }
      ],
      "services": {
        "appinvite_service": {
          "other_platform_oauth_client": [
            {
              "client_id": "658899465592-4itlloc65cfnbum9m84co0bb621ap7l0.apps.googleusercontent.com",
              "client_type": 3
            }
          ]
        }
      }
    }
  ],
  "configuration_version": "1"
}